fasttreeshap/__init__.py
fasttreeshap/_cext.cpython-39-darwin.so
fasttreeshap/_explanation.py
fasttreeshap/_serializable.py
fasttreeshap/datasets.py
fasttreeshap/links.py
fasttreeshap/cext/tree_shap.h
fasttreeshap/explainers/__init__.py
fasttreeshap/explainers/_explainer.py
fasttreeshap/explainers/_tree.py
fasttreeshap/maskers/__init__.py
fasttreeshap/maskers/_composite.py
fasttreeshap/maskers/_fixed.py
fasttreeshap/maskers/_fixed_composite.py
fasttreeshap/maskers/_image.py
fasttreeshap/maskers/_masker.py
fasttreeshap/maskers/_output_composite.py
fasttreeshap/maskers/_tabular.py
fasttreeshap/maskers/_text.py
fasttreeshap/models/__init__.py
fasttreeshap/models/_model.py
fasttreeshap/plots/__init__.py
fasttreeshap/plots/_bar.py
fasttreeshap/plots/_beeswarm.py
fasttreeshap/plots/_benchmark.py
fasttreeshap/plots/_decision.py
fasttreeshap/plots/_embedding.py
fasttreeshap/plots/_force.py
fasttreeshap/plots/_force_matplotlib.py
fasttreeshap/plots/_group_difference.py
fasttreeshap/plots/_heatmap.py
fasttreeshap/plots/_image.py
fasttreeshap/plots/_labels.py
fasttreeshap/plots/_monitoring.py
fasttreeshap/plots/_partial_dependence.py
fasttreeshap/plots/_scatter.py
fasttreeshap/plots/_text.py
fasttreeshap/plots/_utils.py
fasttreeshap/plots/_violin.py
fasttreeshap/plots/_waterfall.py
fasttreeshap/plots/colors/__init__.py
fasttreeshap/plots/colors/_colorconv.py
fasttreeshap/plots/colors/_colors.py
fasttreeshap/plots/resources/bundle.js
fasttreeshap/plots/resources/logoSmallGray.png
fasttreeshap/utils/__init__.py
fasttreeshap/utils/_clustering.py
fasttreeshap/utils/_general.py
fasttreeshap/utils/_keras.py
fasttreeshap/utils/_legacy.py
fasttreeshap/utils/_masked_model.py
fasttreeshap/utils/_show_progress.py
fasttreeshap/utils/image.py
fasttreeshap/utils/transformers.py
fasttreeshap-0.1.6.dist-info/LICENSE
fasttreeshap-0.1.6.dist-info/METADATA
fasttreeshap-0.1.6.dist-info/NOTICE
fasttreeshap-0.1.6.dist-info/WHEEL
fasttreeshap-0.1.6.dist-info/top_level.txt
fasttreeshap-0.1.6.dist-info/RECORD
